{
    "name": "Islamic Empire 78_90 AH",
    "children": [
        {
            "name": "Syria",
            "color": "#e6194b",
            "children": [
                {
                    "name": "Sham",
                    "weight": 20.38,
                    "code": 383
                }
            ]
        },
        {
            "name": "Arabia",
            "color": "#3cb44b",
            "children": [
                {
                    "name": "Arabia",
                    "weight": 0.16,
                    "code": 3
                }
            ]
        },
        {
            "name": "Wasit",
            "color": "#ffe119",
            "children": [
                {
                    "name": "Wasit",
                    "weight": 15.27,
                    "code": 287
                }
            ]
        },
        {
            "name": "Basra",
            "color": "#4363d8",
            "children": [
                {
                    "name": "Fars",
                    "weight": 8.83,
                    "code": 166
                },
                {
                    "name": "Kirman",
                    "weight": 0.11,
                    "code": 2
                },
                {
                    "name": "Ahwaz",
                    "weight": 10.22,
                    "code": 192
                }
            ]
        },
        {
            "name": "Khurasan",
            "color": "#f58231",
            "children": [
                {
                    "name": "Khurasan",
                    "weight": 5.59,
                    "code": 105
                }
            ]
        },
        {
            "name": "Kufa",
            "color": "#46f0f0",
            "children": [
                {
                    "name": "North",
                    "weight": 4.58,
                    "code": 86
                },
                {
                    "name": "Kufa",
                    "weight": 4.47,
                    "code": 84
                },
                {
                    "name": "Jibal",
                    "weight": 11.5,
                    "code": 216
                }
            ]
        },
        {
            "name": "undefined",
            "color": "#f032e6",
            "children": [
                {
                    "name": "undefined",
                    "weight": 3.3,
                    "code": 62
                }
            ]
        }
    ]
}